setup.py
bin/compare_click_models.py
bin/generate_serp.py
bin/run_inference.py
clickmodels/__init__.py
clickmodels/bootstrap.py
clickmodels/config_sample.py
clickmodels/inference.py
clickmodels/input_reader.py
clickmodels.egg-info/PKG-INFO
clickmodels.egg-info/SOURCES.txt
clickmodels.egg-info/dependency_links.txt
clickmodels.egg-info/top_level.txt