Metadata-Version: 1.0
Name: clickmodels
Version: 1.0.2
Summary: Probabilistic models of user behavior on a search engine result page
Home-page: https://github.com/varepsilon/clickmodels
Author: Aleksandr Chuklin
Author-email: UNKNOWN
License: LICENSE
Platform: UNKNOWN
